{
  "version_name": "2.0 DEV 2",
  "version_code": "2.0",
  "file_size": "13MB",
  "downloadLink": "null",
  "changelog": "(30.12.2024)\n• Новый интерфейс\n• Новый интерфейс\n• Новый интерфейс\n• Новый интерфейс\n• Новый интерфейс\n• Новый интерфейс\n• Новый интерфейс\n• Новый интерфейс\n• Новый интерфейс\n• Новый интерфейс\n• Новый интерфейс\n• Новый интерфейс\n• Новый интерфейс\n• Новый интерфейс\n• Новый интерфейс\n• Новый интерфейс\n• Новый интерфейс\n• Новый интерфейс\n• Новый интерфейс\n• Новый интерфейс\n• Новый интерфейс\n• Новый интерфейс\n• Новый интерфейс"
}
